ml_algorithm_selector/__init__.py
ml_algorithm_selector/selector.py
ml_algorithm_selector-0.1.dist-info/LICENSE
ml_algorithm_selector-0.1.dist-info/METADATA
ml_algorithm_selector-0.1.dist-info/WHEEL
ml_algorithm_selector-0.1.dist-info/entry_points.txt
ml_algorithm_selector-0.1.dist-info/top_level.txt
ml_algorithm_selector-0.1.dist-info/RECORD
